irbasis/__init__.py
irbasis/irbasis.h5
irbasis/irbasis.py
irbasis/version
irbasis-2.2.3.dist-info/METADATA
irbasis-2.2.3.dist-info/WHEEL
irbasis-2.2.3.dist-info/top_level.txt
irbasis-2.2.3.dist-info/RECORD
