Metadata-Version: 2.1
Name: irbasis
Version: 2.2.3
Summary: Python libraries for irbasis
Home-page: https://github.com/SpM-lab/irbasis
Author: Kazuyoshi Yoshimi, Hiroshi Shinaoka, Chikano Naoya, Junya Otsuki, Markus Wallerberger
Author-email: h.shinaoka@gmail.com
License: UNKNOWN
Keywords: quantum many-body theory
Platform: UNKNOWN
Classifier: Development Status :: 5 - Production/Stable
Classifier: Intended Audience :: Developers
Classifier: Topic :: Scientific/Engineering
Classifier: License :: OSI Approved :: MIT License
Classifier: Programming Language :: Python :: 2
Classifier: Programming Language :: Python :: 2.7
Classifier: Programming Language :: Python :: 3
Classifier: Programming Language :: Python :: 3.4
Classifier: Programming Language :: Python :: 3.5
Classifier: Programming Language :: Python :: 3.6
Requires-Dist: numpy
Requires-Dist: scipy
Requires-Dist: h5py
Requires-Dist: future
